[
  {
    "annotator": "a",
    "obj_id": "1",
    "obj_type": "Car",
    "psr": {
      "position": {
        "x": 7.640637799264823,
        "y": -2.406875161744324,
        "z": -0.17369568347930917
      },
      "rotation": {
        "x": 0,
        "y": 0,
        "z": -0.07853981633974527
      },
      "scale": {
        "x": 3.932444738456195,
        "y": 2.4329482106208142,
        "z": 2.775254249572754
      }
    }
  },
  {
    "annotator": "a",
    "obj_id": "2",
    "obj_type": "Car",
    "psr": {
      "position": {
        "x": 14.699892109489838,
        "y": -5.45427165609442,
        "z": -0.586582820562981
      },
      "rotation": {
        "x": 0,
        "y": 0,
        "z": -2.7483816154928262
      },
      "scale": {
        "x": 1.8555886489836397,
        "y": 1.1075211229148139,
        "z": 0.6095176724313945
      }
    }
  }
]